{"cameraMode":{"drawMode":0,"name":"Shaded","section":"Shading Mode"},"sceneLighting":false,"audioPlay":false,"sceneViewState":{"m_AlwaysRefresh":false,"showFog":true,"showSkybox":false,"showFlares":true,"showImageEffects":true,"showParticleSystems":true,"showVisualEffectGraphs":true,"m_FxEnabled":true},"in2DMode":false,"pivot":{"x":-1.8812406063079835,"y":7.004917144775391,"z":6.447430610656738},"rotation":{"x":-0.31355345249176028,"y":-0.14397239685058595,"z":0.0481577143073082,"w":-0.9373489022254944},"size":34.88176345825195,"orthographic":false}